clogging
