Metadata-Version: 1.1
Name: clogging
Version: 0.3
Summary: Configurable Logging Boilerplate for the Autologging Module
Home-page: https://github.com/RyanMillerC/clogging
Author: Ryan Miller
Author-email: ryan@devopsmachine.com
License: MIT
Download-URL: https://github.com/RyanMillerC/clogging/archive/0.3.tar.gz
Keywords: logging,yaml,autologging
Platform: UNKNOWN
Classifier: Development Status :: 3 - Alpha
Classifier: Intended Audience :: Developers
Classifier: License :: OSI Approved :: MIT License
Classifier: Operating System :: OS Independent
Classifier: Programming Language :: Python :: 2
Classifier: Programming Language :: Python :: 3
Classifier: Topic :: System :: Logging
